git_annex/__init__.py
git_annex/git-annex
git_annex/magic.mgc
git_annex/py.typed
git_annex.libs/libbz2-5e516f77.so.1.0.4
git_annex.libs/libgmp-4dc20a90.so.10.4.1
git_annex.libs/liblzma-493cb401.so.5.2.5
git_annex.libs/libmagic-1a3f509b.so.1.0.0
git_annex-10.20251215.dist-info/METADATA
git_annex-10.20251215.dist-info/WHEEL
git_annex-10.20251215.dist-info/entry_points.txt
git_annex-10.20251215.dist-info/RECORD
git_annex-10.20251215.dist-info/sboms/auditwheel.cdx.json
